cwb/__init__.py
cwb/__main__.py
cwb/gui_test.py
cwb/wiki.py
cwb/core/__init__.py
cwb/core/api.py
cwb/core/category.py
cwb/core/color_cmdline.py
cwb/core/date.py
cwb/core/diff.py
cwb/core/page.py
cwb/core/query.py
cwb/core/search.py
cwb/core/user.py
cwb-0.0.2.dist-info/LICENSE.md
cwb-0.0.2.dist-info/METADATA
cwb-0.0.2.dist-info/WHEEL
cwb-0.0.2.dist-info/top_level.txt
cwb-0.0.2.dist-info/RECORD
