Metadata-Version: 2.1
Name: cwb
Version: 0.0.2
Summary: mediawiki bot
Home-page: https://gitlab.com/caeruleum/ceruleanwikibot
Author: caeruleum
Author-email: ceruleanxyz@gmail.com
License: UNKNOWN
Platform: UNKNOWN
Classifier: Programming Language :: Python :: 3
Classifier: License :: OSI Approved :: MIT License
Classifier: Operating System :: OS Independent
Requires-Python: >=3.10
License-File: LICENSE.md
